[
  {
    "title": "Best Crypto to buy as investors shift $1.8B to Ethereum ETFs, leaving Bitcoin (BTC) in the dust",
    "description": "Ether ETFs are now drawing capital faster than ever, and in the last five days, they have attracted $1.83 billion, compared to Bitcoin ETFs which attracted only $171 million. Investor confidence is reflected in Ethereum ETFs which have raised 13.6 billion dollars since their introduction 13 months ago.  This shift is happening as Ethereum shows [&#8230;]",
    "url": "https://cyprus-mail.com/2025/08/31/best-crypto-to-buy-as-investors-shift-1-8b-to-ethereum-etfs-leaving-bitcoin-btc-in-the-dust",
    "source": {
      "name": "cyprus-mail"
    },
    "published_at": "2025-08-31T13:30:00+00:00"
  }
]